MANIFEST.in
README.md
setup.cfg
setup.py
Flatipie/__init__.py
Flatipie/__main__.py
Flatipie/build.py
Flatipie/resources.py
Flatipie.egg-info/PKG-INFO
Flatipie.egg-info/SOURCES.txt
Flatipie.egg-info/dependency_links.txt
Flatipie.egg-info/entry_points.txt
Flatipie.egg-info/not-zip-safe
Flatipie.egg-info/requires.txt
Flatipie.egg-info/top_level.txt
Flatipie/create/main.py
Flatipie/create/src/__init__.py
Flatipie/create/src/app.py
Flatipie/create/src/resources/rc.qrc
Flatipie/create/src/resources/icons/icon.ico
Flatipie/widgets/__init__.py
Flatipie/widgets/button.py
Flatipie/widgets/cards.py
Flatipie/widgets/error.py
Flatipie/widgets/lineedit.py
Flatipie/widgets/sidebar.py