Metadata-Version: 2.1
Name: Flatipie
Version: 0.4.2
Summary: An open-source framework for building modern looking desktop applications
Home-page: https://github.com/flatipie/Flatipie
Author: Zenqi
License: MIT
Download-URL: https://github.com/flatipie/Flatipie/tarball/main
Keywords: desktop application,qt,modern application
Platform: Windows
Classifier: Development Status :: 1 - Planning
Classifier: Intended Audience :: Developers
Classifier: Intended Audience :: Education
Classifier: License :: OSI Approved :: MIT License
Classifier: Natural Language :: English
Classifier: Operating System :: Microsoft :: Windows
Classifier: Programming Language :: Python :: 3.5
Classifier: Programming Language :: Python :: 3.6
Classifier: Programming Language :: Python :: 3.7
Classifier: Programming Language :: Python :: 3.8
Classifier: Topic :: Software Development
Classifier: Topic :: Software Development :: Libraries :: Python Modules
Requires-Python: >=3.5
